gev_analysis/__init__.py
gev_analysis/data_handler.py
gev_analysis/gev_analysis.py
gev_analysis/gpd_analysis.py
gev_analysis/normality_var.py
gev_analysis-0.3.4.dist-info/METADATA
gev_analysis-0.3.4.dist-info/WHEEL
gev_analysis-0.3.4.dist-info/top_level.txt
gev_analysis-0.3.4.dist-info/RECORD
